frequency_encoder/__init__.py
frequency_encoder/encoder.py
frequency_encoder-0.1.0.dist-info/LICENSE
frequency_encoder-0.1.0.dist-info/METADATA
frequency_encoder-0.1.0.dist-info/WHEEL
frequency_encoder-0.1.0.dist-info/top_level.txt
frequency_encoder-0.1.0.dist-info/RECORD
